{
  "root_tag": "DLPSTEXTCLASS",
  "namespaces": {},
  "child_elements": [
    "HEADER",
    "TEXT"
  ],
  "element_count": 9390,
  "word_stats": {
    "word_count": 265258,
    "unique_word_count": 7179,
    "top_words": [
      [
        "the",
        16673
      ],
      [
        "of",
        11413
      ],
      [
        "to",
        8488
      ],
      [
        "and",
        7711
      ],
      [
        "or",
        7372
      ],
      [
        "a",
        5873
      ],
      [
        "in",
        4820
      ],
      [
        "for",
        2797
      ],
      [
        "that",
        2581
      ],
      [
        "by",
        2309
      ],
      [
        "information",
        2302
      ],
      [
        "is",
        2302
      ],
      [
        "with",
        2194
      ],
      [
        "be",
        2134
      ],
      [
        "an",
        1955
      ],
      [
        "s",
        1916
      ],
      [
        "from",
        1840
      ],
      [
        "dhs",
        1824
      ],
      [
        "this",
        1818
      ],
      [
        "may",
        1523
      ]
    ],
    "avg_word_length": 5.133658551297228
  }
}