{
  "root_tag": "DLPSTEXTCLASS",
  "namespaces": {},
  "child_elements": [
    "HEADER",
    "TEXT"
  ],
  "element_count": 16047,
  "word_stats": {
    "word_count": 327416,
    "unique_word_count": 8582,
    "top_words": [
      [
        "the",
        26287
      ],
      [
        "of",
        13472
      ],
      [
        "to",
        9038
      ],
      [
        "a",
        7987
      ],
      [
        "or",
        7167
      ],
      [
        "and",
        7114
      ],
      [
        "in",
        5408
      ],
      [
        "for",
        4013
      ],
      [
        "service",
        3818
      ],
      [
        "be",
        3669
      ],
      [
        "postal",
        3331
      ],
      [
        "by",
        3075
      ],
      [
        "is",
        2711
      ],
      [
        "shall",
        2373
      ],
      [
        "that",
        2315
      ],
      [
        "as",
        2206
      ],
      [
        "any",
        2173
      ],
      [
        "s",
        2073
      ],
      [
        "may",
        1964
      ],
      [
        "with",
        1904
      ]
    ],
    "avg_word_length": 5.0087992034598185
  }
}